opengsq/__init__.py
opengsq/binary_reader.py
opengsq/cli.py
opengsq/protocol_base.py
opengsq/protocol_socket.py
opengsq/version.py
opengsq/exceptions/__init__.py
opengsq/exceptions/authentication_exception.py
opengsq/exceptions/invalid_packet_exception.py
opengsq/exceptions/server_not_found_exception.py
opengsq/protocols/__init__.py
opengsq/protocols/aoe1.py
opengsq/protocols/aoe2.py
opengsq/protocols/ase.py
opengsq/protocols/avp2.py
opengsq/protocols/battlefield.py
opengsq/protocols/battlefield2.py
opengsq/protocols/cod1.py
opengsq/protocols/cod4.py
opengsq/protocols/cod5.py
opengsq/protocols/directplay.py
opengsq/protocols/doom3.py
opengsq/protocols/eldewrito.py
opengsq/protocols/eos.py
opengsq/protocols/fivem.py
opengsq/protocols/flatout2.py
opengsq/protocols/gamespy1.py
opengsq/protocols/gamespy2.py
opengsq/protocols/gamespy3.py
opengsq/protocols/gamespy4.py
opengsq/protocols/halo1.py
opengsq/protocols/jediknight.py
opengsq/protocols/kaillera.py
opengsq/protocols/killingfloor.py
opengsq/protocols/minecraft.py
opengsq/protocols/nadeo.py
opengsq/protocols/palworld.py
opengsq/protocols/quake1.py
opengsq/protocols/quake2.py
opengsq/protocols/quake3.py
opengsq/protocols/raknet.py
opengsq/protocols/renegadex.py
opengsq/protocols/samp.py
opengsq/protocols/satisfactory.py
opengsq/protocols/scum.py
opengsq/protocols/source.py
opengsq/protocols/ssc.py
opengsq/protocols/stronghold_ce.py
opengsq/protocols/stronghold_crusader.py
opengsq/protocols/supcom.py
opengsq/protocols/teamspeak3.py
opengsq/protocols/toxikk.py
opengsq/protocols/trackmania_nations.py
opengsq/protocols/udk.py
opengsq/protocols/unreal2.py
opengsq/protocols/ut3.py
opengsq/protocols/vcmp.py
opengsq/protocols/w40kdow.py
opengsq/protocols/warcraft3.py
opengsq/protocols/warfork.py
opengsq/protocols/won.py
opengsq/rcon_protocols/__init__.py
opengsq/rcon_protocols/source_rcon.py
opengsq/responses/__init__.py
opengsq/responses/aoe1/__init__.py
opengsq/responses/aoe1/status.py
opengsq/responses/aoe2/__init__.py
opengsq-3.6.0.dist-info/licenses/LICENSE
opengsq-3.6.0.dist-info/METADATA
opengsq-3.6.0.dist-info/WHEEL
opengsq-3.6.0.dist-info/entry_points.txt
opengsq-3.6.0.dist-info/top_level.txt
opengsq-3.6.0.dist-info/RECORD
