Metadata-Version: 2.4
Name: opengsq
Version: 3.6.0
Summary: 🐍 OpenGSQ - Python library for querying game servers
Home-page: https://github.com/opengsq/opengsq-python
Author: OpenGSQ
License: MIT
Project-URL: Bug Tracker, https://github.com/opengsq/opengsq-python/issues
Project-URL: Source Code, https://github.com/opengsq/opengsq-python
Project-URL: Documentation, https://python.opengsq.com/
Classifier: Development Status :: 5 - Production/Stable
Classifier: Intended Audience :: Developers
Classifier: License :: OSI Approved :: MIT License
Classifier: Operating System :: OS Independent
Classifier: Programming Language :: Python
Classifier: Programming Language :: Python :: 3.9
Classifier: Programming Language :: Python :: 3.10
Classifier: Programming Language :: Python :: 3.11
Classifier: Programming Language :: Python :: 3.12
Classifier: Programming Language :: Python :: 3.13
Classifier: Topic :: Software Development :: Libraries :: Python Modules
Requires-Python: >=3.9
License-File: LICENSE
Requires-Dist: aiohttp<4,>=3.7.4
Dynamic: author
Dynamic: classifier
Dynamic: description
Dynamic: description-content-type
Dynamic: home-page
Dynamic: license
Dynamic: license-file
Dynamic: project-url
Dynamic: requires-dist
Dynamic: requires-python
Dynamic: summary
